pyxtermjs/__init__.py
pyxtermjs/__main__.py
pyxtermjs/app.py
pyxtermjs/index.html
pyxtermjs-0.5.0.2.dist-info/LICENSE
pyxtermjs-0.5.0.2.dist-info/METADATA
pyxtermjs-0.5.0.2.dist-info/WHEEL
pyxtermjs-0.5.0.2.dist-info/entry_points.txt
pyxtermjs-0.5.0.2.dist-info/top_level.txt
pyxtermjs-0.5.0.2.dist-info/RECORD
