Metadata-Version: 2.1
Name: pyxtermjs
Version: 0.5.0.2
Summary: interactive terminal in the browser
Home-page: https://github.com/cs01/pyxtermjs
Author: Chad Smith
Author-email: chadsmith.software@gmail.com
License: License :: OSI Approved :: MIT License
Keywords: xterm,xterm.js,javascript,terminal-emulators,browser,tty,pty,console,terminal
Classifier: Operating System :: OS Independent
Classifier: License :: OSI Approved :: MIT License
Classifier: Programming Language :: Python
Classifier: Programming Language :: Python :: 3.6
Classifier: Programming Language :: Python :: 3.7
Classifier: Programming Language :: Python :: 3 :: Only
Requires-Python: >=3.6
License-File: LICENSE
